jolokia/__init__.py
jolokia/api.py
jolokia/exceptions.py
jolokia/models.py
jolokia/utils/__init__.py
jolokia/utils/decorators.py
jolokia/utils/validators.py
jolokia-0.4.0.dist-info/LICENSE.txt
jolokia-0.4.0.dist-info/METADATA
jolokia-0.4.0.dist-info/WHEEL
jolokia-0.4.0.dist-info/top_level.txt
jolokia-0.4.0.dist-info/RECORD
